{
  "links": {
    "self": "/es/carta/antipasti"
  },
  "data": [
    {
      "type": "articles",
      "id": "antipasti",
      "attributes": {
        "title": "Antipasti",
        "description": "<p>Entrantes tradicionales italianos elaborados con productos frescos.</p>",
        "content": "",
        "class": "",
        "container_class": "container px-5",
        "row_class": "row justify-content-center my-5",
        "col_class": "col-lg-12",
        "wrapper_class": "text-center my-2",
        "title_class": "fw-bolder mb-3",
        "paragraph_class": "lead fw-normal text-muted mb-2",
        "images": [],
        "images_portfolio": [],
        "videos": [],
        "articles": [
          {
            "title": "Insalata con bacalao",
            "slug": "insalata-con-bacalao",
            "description": "<p>Ensalada de brotes tiernos con bacalao escabechado en vinagre de manzana verde, cebolla, pasas, piñones y gajos de naranja.</p>",
            "link": "/es/carta/antipasti/insalata-con-bacalao",
            "icon": "",
            "featured": false,
            "sort": 1,
            "row_class": "row gx-0 mb-1 mb-lg-0 justify-content-center",
            "images": [],
            "images_class": "img-fluid",
            "images_col_class": "",
            "article_col_class": "col-lg-6",
            "article_wrapper_class": "bg-light h-100",
            "article_container_class": "d-flex h-100",
            "article_content_class": "w-100 my-auto text-lg-left",
            "article_title_class": "text-black px-4 mt-4",
            "article_paragraph_class": "mb-0 px-4 text-dark-50",
            "meta": {
              "attributes": {
                "price": {
                  "label": "Precio",
                  "amount": 16.5,
                  "currency": "EUR",
                  "display": { "symbol": "€", "position": "after" }
                },
                "tags": { "values": ["antipasto"] }
              }
            },
            "call_to_action": {
              "title": "Ver más",
              "icon": "bi bi-plus-lg me-2",
              "link": "/es/carta/antipasti/insalata-con-bacalao",
              "class": "btn btn-primary mt-3 mb-3",
              "active": false
            }
          },
          {
            "title": "La parmigiana",
            "slug": "la-parmigiana",
            "description": "<p>Milhojas de berenjenas al horno con mozzarella, tomate y albahaca.</p>",
            "link": "/es/carta/antipasti/la-parmigiana",
            "icon": "",
            "featured": false,
            "sort": 2,
            "row_class": "row gx-0 mb-1 mb-lg-0 justify-content-center",
            "images": [],
            "images_class": "img-fluid",
            "images_col_class": "",
            "article_col_class": "col-lg-6",
            "article_wrapper_class": "bg-light h-100",
            "article_container_class": "d-flex h-100",
            "article_content_class": "w-100 my-auto text-lg-left",
            "article_title_class": "text-black px-4 mt-4",
            "article_paragraph_class": "mb-0 px-4 text-dark-50",
            "meta": {
              "attributes": {
                "price": {
                  "label": "Precio",
                  "amount": 16,
                  "currency": "EUR",
                  "display": { "symbol": "€", "position": "after" }
                },
                "tags": { "values": ["antipasto"] }
              }
            },
            "call_to_action": {
              "title": "Ver más",
              "icon": "bi bi-plus-lg me-2",
              "link": "/es/carta/antipasti/la-parmigiana",
              "class": "btn btn-primary mt-3 mb-3",
              "active": false
            }
          },
          {
            "title": "Tagliata di tonno",
            "slug": "tagliata-di-tonno",
            "description": "<p>Lomo de atún fileteado sobre cama de calabacín a la plancha, brotes de rúcola y chips de cebolla crujiente con emulsión de mostaza antigua.</p>",
            "link": "/es/carta/antipasti/tagliata-di-tonno",
            "icon": "",
            "featured": false,
            "sort": 3,
            "row_class": "row gx-0 mb-1 mb-lg-0 justify-content-center",
            "images": [],
            "images_class": "img-fluid",
            "images_col_class": "",
            "article_col_class": "col-lg-6",
            "article_wrapper_class": "bg-light h-100",
            "article_container_class": "d-flex h-100",
            "article_content_class": "w-100 my-auto text-lg-left",
            "article_title_class": "text-black px-4 mt-4",
            "article_paragraph_class": "mb-0 px-4 text-dark-50",
            "meta": {
              "attributes": {
                "price": {
                  "label": "Precio",
                  "amount": 17.5,
                  "currency": "EUR",
                  "display": { "symbol": "€", "position": "after" }
                },
                "tags": { "values": ["antipasto"] }
              }
            },
            "call_to_action": {
              "title": "Ver más",
              "icon": "bi bi-plus-lg me-2",
              "link": "/es/carta/antipasti/tagliata-di-tonno",
              "class": "btn btn-primary mt-3 mb-3",
              "active": false
            }
          },
          {
            "title": "Burrata Pugliese",
            "slug": "burrata-pugliese",
            "description": "<p>Burrata fresca en emulsión de tomate rama y lámina de parmesano tostado al horno.</p>",
            "link": "/es/carta/antipasti/burrata-pugliese",
            "icon": "",
            "featured": false,
            "sort": 4,
            "row_class": "row gx-0 mb-1 mb-lg-0 justify-content-center",
            "images": [],
            "images_class": "img-fluid",
            "images_col_class": "",
            "article_col_class": "col-lg-6",
            "article_wrapper_class": "bg-light h-100",
            "article_container_class": "d-flex h-100",
            "article_content_class": "w-100 my-auto text-lg-left",
            "article_title_class": "text-black px-4 mt-4",
            "article_paragraph_class": "mb-0 px-4 text-dark-50",
            "meta": {
              "attributes": {
                "price": {
                  "label": "Precio",
                  "amount": 16,
                  "currency": "EUR",
                  "display": { "symbol": "€", "position": "after" }
                },
                "tags": { "values": ["antipasto"] }
              }
            },
            "call_to_action": {
              "title": "Ver más",
              "icon": "bi bi-plus-lg me-2",
              "link": "/es/carta/antipasti/burrata-pugliese",
              "class": "btn btn-primary mt-3 mb-3",
              "active": false
            }
          },
          {
            "title": "Vitello tonnato",
            "slug": "vitello-tonnato",
            "description": "<p>Láminas de ternera asada en salsa de atún, anchoas y alcaparras.</p>",
            "link": "/es/carta/antipasti/vitello-tonnato",
            "icon": "",
            "featured": false,
            "sort": 5,
            "row_class": "row gx-0 mb-1 mb-lg-0 justify-content-center",
            "images": [],
            "images_class": "img-fluid",
            "images_col_class": "",
            "article_col_class": "col-lg-6",
            "article_wrapper_class": "bg-light h-100",
            "article_container_class": "d-flex h-100",
            "article_content_class": "w-100 my-auto text-lg-left",
            "article_title_class": "text-black px-4 mt-4",
            "article_paragraph_class": "mb-0 px-4 text-dark-50",
            "meta": {
              "attributes": {
                "price": {
                  "label": "Precio",
                  "amount": 18,
                  "currency": "EUR",
                  "display": { "symbol": "€", "position": "after" }
                },
                "tags": { "values": ["antipasto"] }
              }
            },
            "call_to_action": {
              "title": "Ver más",
              "icon": "bi bi-plus-lg me-2",
              "link": "/es/carta/antipasti/vitello-tonnato",
              "class": "btn btn-primary mt-3 mb-3",
              "active": false
            }
          },
          {
            "title": "Provolone dolce di Sorrento",
            "slug": "provolone-dolce-di-sorrento",
            "description": "<p>Provolone a la plancha templado con confitura de tomate y filetes de anchoas.</p>",
            "link": "/es/carta/antipasti/provolone-dolce-di-sorrento",
            "icon": "",
            "featured": false,
            "sort": 6,
            "row_class": "row gx-0 mb-1 mb-lg-0 justify-content-center",
            "images": [],
            "images_class": "img-fluid",
            "images_col_class": "",
            "article_col_class": "col-lg-6",
            "article_wrapper_class": "bg-light h-100",
            "article_container_class": "d-flex h-100",
            "article_content_class": "w-100 my-auto text-lg-left",
            "article_title_class": "text-black px-4 mt-4",
            "article_paragraph_class": "mb-0 px-4 text-dark-50",
            "meta": {
              "attributes": {
                "price": {
                  "label": "Precio",
                  "amount": 15,
                  "currency": "EUR",
                  "display": { "symbol": "€", "position": "after" }
                },
                "tags": { "values": ["antipasto"] }
              }
            },
            "call_to_action": {
              "title": "Ver más",
              "icon": "bi bi-plus-lg me-2",
              "link": "/es/carta/antipasti/provolone-dolce-di-sorrento",
              "class": "btn btn-primary mt-3 mb-3",
              "active": false
            }
          },
          {
            "title": "Focaccia",
            "slug": "focaccia",
            "description": "<p>Cesta de focaccia con tomate y orégano.</p>",
            "link": "/es/carta/antipasti/focaccia",
            "icon": "",
            "featured": false,
            "sort": 7,
            "row_class": "row gx-0 mb-1 mb-lg-0 justify-content-center",
            "images": [],
            "images_class": "img-fluid",
            "images_col_class": "",
            "article_col_class": "col-lg-6",
            "article_wrapper_class": "bg-light h-100",
            "article_container_class": "d-flex h-100",
            "article_content_class": "w-100 my-auto text-lg-left",
            "article_title_class": "text-black px-4 mt-4",
            "article_paragraph_class": "mb-0 px-4 text-dark-50",
            "meta": {
              "attributes": {
                "price": {
                  "label": "Precio",
                  "amount": 9.9,
                  "currency": "EUR",
                  "display": { "symbol": "€", "position": "after" }
                },
                "tags": { "values": ["antipasto"] }
              }
            },
            "call_to_action": {
              "title": "Ver más",
              "icon": "bi bi-plus-lg me-2",
              "link": "/es/carta/antipasti/focaccia",
              "class": "btn btn-primary mt-3 mb-3",
              "active": false
            }
          },
          {
            "title": "Servicio AOVE",
            "slug": "servicio-aove",
            "description": "<p>Aceite de oliva virgen extra de alta calidad, ideal para acompañar nuestra focaccia casera y realzar el sabor de cada plato.</p>",
            "link": "/es/carta/antipasti/servicio-aove",
            "icon": "",
            "featured": false,
            "sort": 8,
            "row_class": "row gx-0 mb-1 mb-lg-0 justify-content-center",
            "images": [],
            "images_class": "img-fluid",
            "images_col_class": "",
            "article_col_class": "col-lg-6",
            "article_wrapper_class": "bg-light h-100",
            "article_container_class": "d-flex h-100",
            "article_content_class": "w-100 my-auto text-lg-left",
            "article_title_class": "text-black px-4 mt-4",
            "article_paragraph_class": "mb-0 px-4 text-dark-50",
            "meta": {
              "attributes": {
                "price": {
                  "label": "Precio",
                  "amount": 5,
                  "currency": "EUR",
                  "display": { "symbol": "€", "position": "after" }
                },
                "tags": { "values": ["antipasto"] }
              }
            },
            "call_to_action": {
              "title": "Ver más",
              "icon": "bi bi-plus-lg me-2",
              "link": "/es/carta/antipasti/servicio-aove",
              "class": "btn btn-primary mt-3 mb-3",
              "active": false
            }
          }
        ],
        "call_to_action": {
            "title": "Carta",
            "icon": "bi bi-book me-2",
            "link": "/es/carta",
            "class": "btn btn-danger",
            "active": true
        }
      },
      "links": {
        "self": "/es/carta/antipasti"
      }
    }
  ]
}
